shella/__init__.py
shella/cmd.py
shella/command.py
shella/term.py
shella-1.0.3.dist-info/METADATA
shella-1.0.3.dist-info/WHEEL
shella-1.0.3.dist-info/top_level.txt
shella-1.0.3.dist-info/RECORD
