Metadata-Version: 2.1
Name: shella
Version: 1.0.3
Summary: An asynchronous Interactive shell
Home-page: UNKNOWN
Author: Malte Gruber
Author-email: <contact@maltegruber.com>
License: UNKNOWN
Keywords: python,first package
Platform: UNKNOWN
Classifier: Development Status :: 3 - Alpha
Classifier: Intended Audience :: End Users/Desktop
Classifier: Programming Language :: Python :: 3
Classifier: Operating System :: MacOS :: MacOS X
Classifier: Operating System :: POSIX :: Linux 
Requires-Dist: aiofiles
